{
  "generator-jhipster": {
    "authenticationType": "jwt",
    "clientFramework": "angularX",
    "serverPort": "8080",
    "serviceDiscoveryType": "eureka",
    "skipUserManagement": false,
    "withAdminUi": true,
    "baseName": "gateway",
    "buildTool": "maven",
    "databaseType": "sql",
    "devDatabaseType": "h2Disk",
    "cacheProvider": "no",
    "enableHibernateCache": false,
    "enableSwaggerCodegen": false,
    "enableTranslation": true,
    "jhiPrefix": "jhi",
    "languages": ["en"],
    "messageBroker": false,
    "prodDatabaseType": "oracle",
    "searchEngine": false,
    "skipClient": false,
    "testFrameworks": ["cypress"],
    "websocket": false,
    "enableGradleEnterprise": false,
    "gradleEnterpriseHost": "",
    "applicationType": "gateway",
    "packageName": "com.leap.training.gateway",
    "packageFolder": "com/leap/training/gateway",
    "jhipsterVersion": "7.3.0",
    "skipServer": false,
    "clientPackageManager": "npm",
    "dtoSuffix": "DTO",
    "entitySuffix": "",
    "reactive": true,
    "clientTheme": "none",
    "clientThemeVariant": "",
    "applicationIndex": 1,
    "skipCheckLengthOfIdentifier": false,
    "skipFakeData": false,
    "blueprints": [],
    "otherModules": [],
    "pages": [],
    "creationTimestamp": 1666611409354,
    "jwtSecretKey": "ZTRkODZjMWMyYzQ0NjM0Zjk1ZmVmN2YxYzNkNWFhMWEzOGFiMjA0Njk2MjkzODJiNzFlZWUyZGIxZjNhYmVjMjNjNWNmOGRhNTA0MzE2OTM5YjNmYTNmZDM3Mzk3MTU5MjZhNTUwNDk0ZGNiMDJlM2JkODQ2YzhiZDgxYWIyMTg=",
    "devServerPort": 4201,
    "nativeLanguage": "en",
    "entities": []
  }
}
